[
  {
    "color": "#ab63fa",
    "SectorNames": "Rubber",
    "Export": [
      598032,
      754225,
      1047516,
      1208450,
      309440,
      407564,
      925067,
      1440568,
      2038773,
      1800037,
      1804827,
      2448001,
      2862862,
      2128771,
      2182816,
      3372466,
      2334492,
      3495327,
      2170972,
      2822836,
      3773848,
      2906428,
      3311632,
      1425185,
      446442,
      0,
      0,
      1711580,
      3051324,
      996151
    ]
  },
  {
    "color": "#FECB52",
    "SectorNames": "Cocoa Beans and products",
    "Export": [
      199251,
      60171,
      0,
      0,
      0,
      0,
      75323,
      62605,
      170110,
      158323,
      219236,
      103129,
      70207,
      117161,
      110572,
      206523,
      60255,
      70320,
      239423,
      536496,
      1036571,
      1371794,
      1164719,
      387010,
      198801,
      237901,
      1687696,
      573458,
      802939,
      266859
    ]
  },
  {
    "color": "#00cc96",
    "SectorNames": "Other transport equipment",
    "Export": [
      118509,
      52759,
      66277,
      79155,
      76905,
      63999,
      80793,
      137749,
      155899,
      231351,
      1016748,
      802632,
      1010625,
      658606,
      394694,
      802418,
      200384,
      723110,
      58716,
      32891,
      160979,
      37206,
      45032,
      51642,
      41053,
      35274,
      35836,
      36711,
      43243,
      36752
    ]
  },
  {
    "color": "#636efa",
    "SectorNames": "Copper ores",
    "Export": [
      1579418,
      325368,
      94467,
      455129,
      337585,
      332141,
      392094,
      275424,
      131545,
      126455,
      215246,
      271187,
      297927,
      262017,
      114512,
      101960,
      137172,
      158593,
      27512,
      24019,
      33289,
      55748,
      79063,
      116170,
      62162,
      83364,
      87522,
      115864,
      165597,
      167726
    ]
  },
  {
    "color": "#19d3f3",
    "SectorNames": "Rubber products",
    "Export": [
      88231,
      26587,
      51546,
      38038,
      31221,
      32187,
      419,
      3738,
      2191,
      154630,
      189594,
      1549159,
      1041636,
      54459,
      38522,
      482555,
      824798,
      187244,
      26519,
      17527,
      47662,
      52239,
      60863,
      68831,
      73437,
      73082,
      78272,
      79122,
      79564,
      82241
    ]
  },
  {
    "color": "#EF553B",
    "SectorNames": "Basic iron and steel",
    "Export": [
      127013,
      38591,
      46235,
      44601,
      37702,
      35209,
      40177,
      68914,
      104748,
      116913,
      430072,
      464228,
      530901,
      354461,
      271392,
      308863,
      213729,
      356746,
      12448,
      15302,
      17521,
      12917,
      15229,
      17631,
      19406,
      19267,
      21181,
      21847,
      22468,
      22682
    ]
  },
  {
    "color": "#00cc96",
    "SectorNames": "Leather and footwear",
    "Export": [
      73092,
      3551,
      6395,
      20518,
      16513,
      21810,
      31098,
      35445,
      52673,
      63206,
      179314,
      250648,
      364147,
      260228,
      136482,
      132128,
      177742,
      148393,
      15487,
      11393,
      13737,
      16171,
      24028,
      36808,
      42388,
      36714,
      49212,
      51750,
      45437,
      54043
    ]
  },
  {
    "color": "#FECB52",
    "SectorNames": "Publishing",
    "Export": [
      65717,
      24193,
      40058,
      29806,
      27475,
      30417,
      27342,
      38450,
      47432,
      67894,
      232113,
      312995,
      463193,
      264464,
      44076,
      68272,
      106486,
      87024,
      3175,
      2030,
      3028,
      3350,
      652,
      866,
      880,
      721,
      1066,
      1248,
      1161,
      1389
    ]
  },
  {
    "color": "#FFA15A",
    "SectorNames": "Computers; electronic products; optical and precision instruments",
    "Export": [
      44594,
      18928,
      27041,
      19889,
      19199,
      15100,
      13384,
      24813,
      45358,
      39841,
      213080,
      286873,
      252889,
      248712,
      249781,
      114656,
      24755,
      87748,
      3362,
      1253,
      1574,
      822,
      1209,
      1627,
      1877,
      1670,
      1528,
      1102,
      586,
      769
    ]
  },
  {
    "color": "#FECB52",
    "SectorNames": "Cement, lime and plaster products",
    "Export": [
      3598,
      893,
      1609,
      1729,
      1500,
      1660,
      2506,
      656,
      893,
      19784,
      345304,
      54023,
      55861,
      205908,
      87481,
      61902,
      241004,
      79036,
      3644,
      2463,
      4629,
      8322,
      12263,
      15975,
      17731,
      22453,
      25290,
      26394,
      24991,
      28300
    ]
  },
  {
    "color": "#cccccc",
    "SectorNames": "Other",
    "Export": [
      927485,
      180000,
      263992,
      227515,
      213612,
      343091,
      300712,
      283237,
      306316,
      404764,
      1292968,
      1389993,
      1687428,
      912939,
      602891,
      590283,
      965584,
      594579,
      95990,
      83604,
      88118,
      134850,
      199503,
      255999,
      211262,
      168192,
      245883,
      296629,
      287337,
      336010
    ]
  }
]